safetypy/__init__.py
safetypy/safetypy.py
tools/__init__.py
tools/export_users/__init__.py
tools/export_users/export_users.py
tools/exporter/__init__.py
tools/exporter/csvExporter.py
tools/exporter/exporter.py
tools/import_grs/__init__.py
tools/import_grs/import_grs.py
tools/sync_users/__init__.py
tools/sync_users/sync_users.py
safetyculture_sdk_python-4.2.1.dist-info/LICENSE
safetyculture_sdk_python-4.2.1.dist-info/METADATA
safetyculture_sdk_python-4.2.1.dist-info/WHEEL
safetyculture_sdk_python-4.2.1.dist-info/entry_points.txt
safetyculture_sdk_python-4.2.1.dist-info/top_level.txt
safetyculture_sdk_python-4.2.1.dist-info/RECORD
