Metadata-Version: 2.1
Name: safetyculture-sdk-python
Version: 4.2.1
Summary: iAuditor Python SDK and integration tools
Home-page: https://github.com/SafetyCulture/safetyculture-sdk-python
Author: SafetyCulture
Author-email: integrations@safetyculture.io
License: UNKNOWN
Platform: UNKNOWN
Requires-Dist: python-dateutil (>=2.5.0)
Requires-Dist: pytz (>=2015.7)
Requires-Dist: tzlocal (>=1.3)
Requires-Dist: unicodecsv (>=0.14.1)
Requires-Dist: requests (>=2.10.0)
Requires-Dist: pyyaml (>=3.11)
Requires-Dist: future (>=0.16.0)
Requires-Dist: xlrd (==1.1.0)
Requires-Dist: pyOpenSSL (>=17.5.0)
Requires-Dist: virtualtime (==1.6)
